setup.py
pyrainbow.egg-info/PKG-INFO
pyrainbow.egg-info/SOURCES.txt
pyrainbow.egg-info/dependency_links.txt
pyrainbow.egg-info/requires.txt
pyrainbow.egg-info/top_level.txt
rainbow/__init__.py
rainbow/avahi.py
rainbow/broker.py
rainbow/dealer.py
rainbow/index.html
rainbow/rainbow.service
rainbow/singleton.py
rainbow/webserver.py
test/test_call.py
test/test_json_rpc.py