Metadata-Version: 1.1
Name: pyrainbow
Version: 0.0.7
Summary: 
